<?xml version="1.0"?>
<EmbeddedProfile xmlns:xsd="http://www.w3.org/2001/XMLSchema" xmlns:xsi="http://www.w3.org/2001/XMLSchema-instance">
  <ToolchainID>com.visualgdb.arm-eabi</ToolchainID>
  <ToolchainVersion>
    <GCC>10.3.1</GCC>
    <GDB>10.2.90</GDB>
    <Revision>1</Revision>
  </ToolchainVersion>
  <BspID>com.sysprogs.arm.stm32</BspID>
  <BspVersion>2022.01</BspVersion>
  <McuID>STM32F103VE</McuID>
  <MCUDefinitionFile>STM32F1xxxx/DeviceDefinitions/stm32f103xe.xml</MCUDefinitionFile>
  <MCUProperties>
    <Entries>
      <KeyValue>
        <Key>com.sysprogs.bspoptions.primary_memory</Key>
        <Value>flash</Value>
      </KeyValue>
      <KeyValue>
        <Key>com.sysprogs.mcuoptions.ignore_startup_file</Key>
      </KeyValue>
      <KeyValue>
        <Key>com.sysprogs.toolchainoptions.arm.libctype</Key>
        <Value>--specs=nano.specs</Value>
      </KeyValue>
      <KeyValue>
        <Key>com.sysprogs.toolchainoptions.arm.syscallspecs</Key>
        <Value>--specs=nosys.specs</Value>
      </KeyValue>
    </Entries>
  </MCUProperties>
  <BSPSourceFolderName>Device-specific files</BSPSourceFolderName>
  <MCUMakFile>stm32.mak</MCUMakFile>
  <ReferencedFrameworks />
  <FrameworkProperties>
    <Entries />
  </FrameworkProperties>
  <TestFrameworkProperties>
    <Entries />
  </TestFrameworkProperties>
  <ImportedProject>
    <ImporterID>com.sysprogs.project_importers.keil</ImporterID>
    <RelativeProjectPath>BH-F103.uvprojx</RelativeProjectPath>
    <AllDependencies>
      <ProjectDependency>
        <RelativePath>BH-F103.uvprojx</RelativePath>
        <Timestamp>132873194611359759</Timestamp>
      </ProjectDependency>
    </AllDependencies>
    <RootDirectory>
      <Subdirectories>
        <VirtualDirectorySnapshot>
          <Name>STARTUP</Name>
          <Files />
        </VirtualDirectorySnapshot>
        <VirtualDirectorySnapshot>
          <Name>CMSIS</Name>
          <Files>
            <VirtualFileSnapshot>
              <RelativePath>..\Libraries\CMSIS\core_cm3.c</RelativePath>
            </VirtualFileSnapshot>
            <VirtualFileSnapshot>
              <RelativePath>..\Libraries\CMSIS\system_stm32f10x.c</RelativePath>
            </VirtualFileSnapshot>
            <VirtualFileSnapshot>
              <RelativePath>..\Libraries\CMSIS\core_cm3.h</RelativePath>
            </VirtualFileSnapshot>
            <VirtualFileSnapshot>
              <RelativePath>..\Libraries\CMSIS\stm32f10x.h</RelativePath>
            </VirtualFileSnapshot>
            <VirtualFileSnapshot>
              <RelativePath>..\Libraries\CMSIS\system_stm32f10x.h</RelativePath>
            </VirtualFileSnapshot>
          </Files>
        </VirtualDirectorySnapshot>
        <VirtualDirectorySnapshot>
          <Name>FWLB</Name>
          <Files>
            <VirtualFileSnapshot>
              <RelativePath>..\Libraries\FWlib\src\misc.c</RelativePath>
            </VirtualFileSnapshot>
            <VirtualFileSnapshot>
              <RelativePath>..\Libraries\FWlib\src\stm32f10x_adc.c</RelativePath>
            </VirtualFileSnapshot>
            <VirtualFileSnapshot>
              <RelativePath>..\Libraries\FWlib\src\stm32f10x_bkp.c</RelativePath>
            </VirtualFileSnapshot>
            <VirtualFileSnapshot>
              <RelativePath>..\Libraries\FWlib\src\stm32f10x_can.c</RelativePath>
            </VirtualFileSnapshot>
            <VirtualFileSnapshot>
              <RelativePath>..\Libraries\FWlib\src\stm32f10x_cec.c</RelativePath>
            </VirtualFileSnapshot>
            <VirtualFileSnapshot>
              <RelativePath>..\Libraries\FWlib\src\stm32f10x_crc.c</RelativePath>
            </VirtualFileSnapshot>
            <VirtualFileSnapshot>
              <RelativePath>..\Libraries\FWlib\src\stm32f10x_dac.c</RelativePath>
            </VirtualFileSnapshot>
            <VirtualFileSnapshot>
              <RelativePath>..\Libraries\FWlib\src\stm32f10x_dbgmcu.c</RelativePath>
            </VirtualFileSnapshot>
            <VirtualFileSnapshot>
              <RelativePath>..\Libraries\FWlib\src\stm32f10x_dma.c</RelativePath>
            </VirtualFileSnapshot>
            <VirtualFileSnapshot>
              <RelativePath>..\Libraries\FWlib\src\stm32f10x_exti.c</RelativePath>
            </VirtualFileSnapshot>
            <VirtualFileSnapshot>
              <RelativePath>..\Libraries\FWlib\src\stm32f10x_flash.c</RelativePath>
            </VirtualFileSnapshot>
            <VirtualFileSnapshot>
              <RelativePath>..\Libraries\FWlib\src\stm32f10x_fsmc.c</RelativePath>
            </VirtualFileSnapshot>
            <VirtualFileSnapshot>
              <RelativePath>..\Libraries\FWlib\src\stm32f10x_gpio.c</RelativePath>
            </VirtualFileSnapshot>
            <VirtualFileSnapshot>
              <RelativePath>..\Libraries\FWlib\src\stm32f10x_i2c.c</RelativePath>
            </VirtualFileSnapshot>
            <VirtualFileSnapshot>
              <RelativePath>..\Libraries\FWlib\src\stm32f10x_iwdg.c</RelativePath>
            </VirtualFileSnapshot>
            <VirtualFileSnapshot>
              <RelativePath>..\Libraries\FWlib\src\stm32f10x_pwr.c</RelativePath>
            </VirtualFileSnapshot>
            <VirtualFileSnapshot>
              <RelativePath>..\Libraries\FWlib\src\stm32f10x_rcc.c</RelativePath>
            </VirtualFileSnapshot>
            <VirtualFileSnapshot>
              <RelativePath>..\Libraries\FWlib\src\stm32f10x_rtc.c</RelativePath>
            </VirtualFileSnapshot>
            <VirtualFileSnapshot>
              <RelativePath>..\Libraries\FWlib\src\stm32f10x_sdio.c</RelativePath>
            </VirtualFileSnapshot>
            <VirtualFileSnapshot>
              <RelativePath>..\Libraries\FWlib\src\stm32f10x_spi.c</RelativePath>
            </VirtualFileSnapshot>
            <VirtualFileSnapshot>
              <RelativePath>..\Libraries\FWlib\src\stm32f10x_tim.c</RelativePath>
            </VirtualFileSnapshot>
            <VirtualFileSnapshot>
              <RelativePath>..\Libraries\FWlib\src\stm32f10x_usart.c</RelativePath>
            </VirtualFileSnapshot>
            <VirtualFileSnapshot>
              <RelativePath>..\Libraries\FWlib\src\stm32f10x_wwdg.c</RelativePath>
            </VirtualFileSnapshot>
          </Files>
        </VirtualDirectorySnapshot>
        <VirtualDirectorySnapshot>
          <Name>USER</Name>
          <Files>
            <VirtualFileSnapshot>
              <RelativePath>..\User\main.c</RelativePath>
            </VirtualFileSnapshot>
            <VirtualFileSnapshot>
              <RelativePath>..\User\palette.c</RelativePath>
            </VirtualFileSnapshot>
            <VirtualFileSnapshot>
              <RelativePath>..\User\stm32f10x_it.c</RelativePath>
            </VirtualFileSnapshot>
            <VirtualFileSnapshot>
              <RelativePath>..\User\usart\bsp_usart.c</RelativePath>
            </VirtualFileSnapshot>
            <VirtualFileSnapshot>
              <RelativePath>..\User\lcd\bsp_ili9341_lcd.c</RelativePath>
            </VirtualFileSnapshot>
            <VirtualFileSnapshot>
              <RelativePath>..\User\lcd\bsp_xpt2046_lcd.c</RelativePath>
            </VirtualFileSnapshot>
            <VirtualFileSnapshot>
              <RelativePath>..\User\font\fonts.c</RelativePath>
            </VirtualFileSnapshot>
            <VirtualFileSnapshot>
              <RelativePath>..\User\flash\bsp_spi_flash.c</RelativePath>
            </VirtualFileSnapshot>
            <VirtualFileSnapshot>
              <RelativePath>..\User\led\bsp_led.c</RelativePath>
            </VirtualFileSnapshot>
          </Files>
        </VirtualDirectorySnapshot>
        <VirtualDirectorySnapshot>
          <Name>DOC</Name>
          <Files>
            <VirtualFileSnapshot>
              <RelativePath>..\Doc\readme.txt</RelativePath>
            </VirtualFileSnapshot>
          </Files>
        </VirtualDirectorySnapshot>
        <VirtualDirectorySnapshot>
          <Name>LVGL</Name>
          <Subdirectories>
            <VirtualDirectorySnapshot>
              <Name>CORE</Name>
              <Files>
                <VirtualFileSnapshot>
                  <RelativePath>..\User\lvgl\src\core\lv_disp.c</RelativePath>
                </VirtualFileSnapshot>
                <VirtualFileSnapshot>
                  <RelativePath>..\User\lvgl\src\core\lv_event.c</RelativePath>
                </VirtualFileSnapshot>
                <VirtualFileSnapshot>
                  <RelativePath>..\User\lvgl\src\core\lv_group.c</RelativePath>
                </VirtualFileSnapshot>
                <VirtualFileSnapshot>
                  <RelativePath>..\User\lvgl\src\core\lv_indev.c</RelativePath>
                </VirtualFileSnapshot>
                <VirtualFileSnapshot>
                  <RelativePath>..\User\lvgl\src\core\lv_indev_scroll.c</RelativePath>
                </VirtualFileSnapshot>
                <VirtualFileSnapshot>
                  <RelativePath>..\User\lvgl\src\core\lv_obj.c</RelativePath>
                </VirtualFileSnapshot>
                <VirtualFileSnapshot>
                  <RelativePath>..\User\lvgl\src\core\lv_obj_class.c</RelativePath>
                </VirtualFileSnapshot>
                <VirtualFileSnapshot>
                  <RelativePath>..\User\lvgl\src\core\lv_obj_draw.c</RelativePath>
                </VirtualFileSnapshot>
                <VirtualFileSnapshot>
                  <RelativePath>..\User\lvgl\src\core\lv_obj_pos.c</RelativePath>
                </VirtualFileSnapshot>
                <VirtualFileSnapshot>
                  <RelativePath>..\User\lvgl\src\core\lv_obj_scroll.c</RelativePath>
                </VirtualFileSnapshot>
                <VirtualFileSnapshot>
                  <RelativePath>..\User\lvgl\src\core\lv_obj_style.c</RelativePath>
                </VirtualFileSnapshot>
                <VirtualFileSnapshot>
                  <RelativePath>..\User\lvgl\src\core\lv_obj_style_gen.c</RelativePath>
                </VirtualFileSnapshot>
                <VirtualFileSnapshot>
                  <RelativePath>..\User\lvgl\src\core\lv_obj_tree.c</RelativePath>
                </VirtualFileSnapshot>
                <VirtualFileSnapshot>
                  <RelativePath>..\User\lvgl\src\core\lv_refr.c</RelativePath>
                </VirtualFileSnapshot>
                <VirtualFileSnapshot>
                  <RelativePath>..\User\lvgl\src\core\lv_theme.c</RelativePath>
                </VirtualFileSnapshot>
              </Files>
            </VirtualDirectorySnapshot>
            <VirtualDirectorySnapshot>
              <Name>DRAW</Name>
              <Files>
                <VirtualFileSnapshot>
                  <RelativePath>..\User\lvgl\src\draw\lv_draw.c</RelativePath>
                </VirtualFileSnapshot>
                <VirtualFileSnapshot>
                  <RelativePath>..\User\lvgl\src\draw\lv_draw_arc.c</RelativePath>
                </VirtualFileSnapshot>
                <VirtualFileSnapshot>
                  <RelativePath>..\User\lvgl\src\draw\lv_draw_img.c</RelativePath>
                </VirtualFileSnapshot>
                <VirtualFileSnapshot>
                  <RelativePath>..\User\lvgl\src\draw\lv_draw_label.c</RelativePath>
                </VirtualFileSnapshot>
                <VirtualFileSnapshot>
                  <RelativePath>..\User\lvgl\src\draw\lv_draw_line.c</RelativePath>
                </VirtualFileSnapshot>
                <VirtualFileSnapshot>
                  <RelativePath>..\User\lvgl\src\draw\lv_draw_mask.c</RelativePath>
                </VirtualFileSnapshot>
                <VirtualFileSnapshot>
                  <RelativePath>..\User\lvgl\src\draw\lv_draw_rect.c</RelativePath>
                </VirtualFileSnapshot>
                <VirtualFileSnapshot>
                  <RelativePath>..\User\lvgl\src\draw\lv_draw_triangle.c</RelativePath>
                </VirtualFileSnapshot>
                <VirtualFileSnapshot>
                  <RelativePath>..\User\lvgl\src\draw\lv_img_buf.c</RelativePath>
                </VirtualFileSnapshot>
                <VirtualFileSnapshot>
                  <RelativePath>..\User\lvgl\src\draw\lv_img_cache.c</RelativePath>
                </VirtualFileSnapshot>
                <VirtualFileSnapshot>
                  <RelativePath>..\User\lvgl\src\draw\lv_img_decoder.c</RelativePath>
                </VirtualFileSnapshot>
                <VirtualFileSnapshot>
                  <RelativePath>..\User\lvgl\src\draw\sw\lv_draw_sw.c</RelativePath>
                </VirtualFileSnapshot>
                <VirtualFileSnapshot>
                  <RelativePath>..\User\lvgl\src\draw\sw\lv_draw_sw_arc.c</RelativePath>
                </VirtualFileSnapshot>
                <VirtualFileSnapshot>
                  <RelativePath>..\User\lvgl\src\draw\sw\lv_draw_sw_blend.c</RelativePath>
                </VirtualFileSnapshot>
                <VirtualFileSnapshot>
                  <RelativePath>..\User\lvgl\src\draw\sw\lv_draw_sw_img.c</RelativePath>
                </VirtualFileSnapshot>
                <VirtualFileSnapshot>
                  <RelativePath>..\User\lvgl\src\draw\sw\lv_draw_sw_letter.c</RelativePath>
                </VirtualFileSnapshot>
                <VirtualFileSnapshot>
                  <RelativePath>..\User\lvgl\src\draw\sw\lv_draw_sw_line.c</RelativePath>
                </VirtualFileSnapshot>
                <VirtualFileSnapshot>
                  <RelativePath>..\User\lvgl\src\draw\sw\lv_draw_sw_polygon.c</RelativePath>
                </VirtualFileSnapshot>
                <VirtualFileSnapshot>
                  <RelativePath>..\User\lvgl\src\draw\sw\lv_draw_sw_rect.c</RelativePath>
                </VirtualFileSnapshot>
                <VirtualFileSnapshot>
                  <RelativePath>..\User\lvgl\src\draw\stm32_dma2d\lv_gpu_stm32_dma2d.c</RelativePath>
                </VirtualFileSnapshot>
              </Files>
            </VirtualDirectorySnapshot>
            <VirtualDirectorySnapshot>
              <Name>EXTRA</Name>
              <Files>
                <VirtualFileSnapshot>
                  <RelativePath>..\User\lvgl\src\extra\lv_extra.c</RelativePath>
                </VirtualFileSnapshot>
                <VirtualFileSnapshot>
                  <RelativePath>..\User\lvgl\src\extra\layouts\flex\lv_flex.c</RelativePath>
                </VirtualFileSnapshot>
                <VirtualFileSnapshot>
                  <RelativePath>..\User\lvgl\src\extra\layouts\grid\lv_grid.c</RelativePath>
                </VirtualFileSnapshot>
                <VirtualFileSnapshot>
                  <RelativePath>..\User\lvgl\src\extra\libs\bmp\lv_bmp.c</RelativePath>
                </VirtualFileSnapshot>
                <VirtualFileSnapshot>
                  <RelativePath>..\User\lvgl\src\extra\libs\ffmpeg\lv_ffmpeg.c</RelativePath>
                </VirtualFileSnapshot>
                <VirtualFileSnapshot>
                  <RelativePath>..\User\lvgl\src\extra\themes\basic\lv_theme_basic.c</RelativePath>
                </VirtualFileSnapshot>
                <VirtualFileSnapshot>
                  <RelativePath>..\User\lvgl\src\extra\themes\default\lv_theme_default.c</RelativePath>
                </VirtualFileSnapshot>
                <VirtualFileSnapshot>
                  <RelativePath>..\User\lvgl\src\extra\themes\mono\lv_theme_mono.c</RelativePath>
                </VirtualFileSnapshot>
                <VirtualFileSnapshot>
                  <RelativePath>..\User\lvgl\src\extra\widgets\calendar\lv_calendar.c</RelativePath>
                </VirtualFileSnapshot>
                <VirtualFileSnapshot>
                  <RelativePath>..\User\lvgl\src\extra\widgets\calendar\lv_calendar_header_arrow.c</RelativePath>
                </VirtualFileSnapshot>
                <VirtualFileSnapshot>
                  <RelativePath>..\User\lvgl\src\extra\widgets\calendar\lv_calendar_header_dropdown.c</RelativePath>
                </VirtualFileSnapshot>
                <VirtualFileSnapshot>
                  <RelativePath>..\User\lvgl\src\extra\widgets\chart\lv_chart.c</RelativePath>
                </VirtualFileSnapshot>
                <VirtualFileSnapshot>
                  <RelativePath>..\User\lvgl\src\extra\widgets\colorwheel\lv_colorwheel.c</RelativePath>
                </VirtualFileSnapshot>
                <VirtualFileSnapshot>
                  <RelativePath>..\User\lvgl\src\extra\widgets\imgbtn\lv_imgbtn.c</RelativePath>
                </VirtualFileSnapshot>
                <VirtualFileSnapshot>
                  <RelativePath>..\User\lvgl\src\extra\widgets\led\lv_led.c</RelativePath>
                </VirtualFileSnapshot>
                <VirtualFileSnapshot>
                  <RelativePath>..\User\lvgl\src\extra\widgets\list\lv_list.c</RelativePath>
                </VirtualFileSnapshot>
                <VirtualFileSnapshot>
                  <RelativePath>..\User\lvgl\src\extra\widgets\menu\lv_menu.c</RelativePath>
                </VirtualFileSnapshot>
                <VirtualFileSnapshot>
                  <RelativePath>..\User\lvgl\src\extra\widgets\meter\lv_meter.c</RelativePath>
                </VirtualFileSnapshot>
                <VirtualFileSnapshot>
                  <RelativePath>..\User\lvgl\src\extra\widgets\msgbox\lv_msgbox.c</RelativePath>
                </VirtualFileSnapshot>
                <VirtualFileSnapshot>
                  <RelativePath>..\User\lvgl\src\extra\widgets\span\lv_span.c</RelativePath>
                </VirtualFileSnapshot>
                <VirtualFileSnapshot>
                  <RelativePath>..\User\lvgl\src\extra\widgets\spinbox\lv_spinbox.c</RelativePath>
                </VirtualFileSnapshot>
                <VirtualFileSnapshot>
                  <RelativePath>..\User\lvgl\src\extra\widgets\spinner\lv_spinner.c</RelativePath>
                </VirtualFileSnapshot>
                <VirtualFileSnapshot>
                  <RelativePath>..\User\lvgl\src\extra\widgets\tabview\lv_tabview.c</RelativePath>
                </VirtualFileSnapshot>
                <VirtualFileSnapshot>
                  <RelativePath>..\User\lvgl\src\extra\widgets\tileview\lv_tileview.c</RelativePath>
                </VirtualFileSnapshot>
                <VirtualFileSnapshot>
                  <RelativePath>..\User\lvgl\src\extra\widgets\win\lv_win.c</RelativePath>
                </VirtualFileSnapshot>
                <VirtualFileSnapshot>
                  <RelativePath>..\User\lvgl\src\extra\widgets\animimg\lv_animimg.c</RelativePath>
                </VirtualFileSnapshot>
                <VirtualFileSnapshot>
                  <RelativePath>..\User\lvgl\src\extra\widgets\keyboard\lv_keyboard.c</RelativePath>
                </VirtualFileSnapshot>
              </Files>
            </VirtualDirectorySnapshot>
            <VirtualDirectorySnapshot>
              <Name>FONT</Name>
              <Files>
                <VirtualFileSnapshot>
                  <RelativePath>..\User\lvgl\src\font\lv_font.c</RelativePath>
                </VirtualFileSnapshot>
                <VirtualFileSnapshot>
                  <RelativePath>..\User\lvgl\src\font\lv_font_dejavu_16_persian_hebrew.c</RelativePath>
                </VirtualFileSnapshot>
                <VirtualFileSnapshot>
                  <RelativePath>..\User\lvgl\src\font\lv_font_fmt_txt.c</RelativePath>
                </VirtualFileSnapshot>
                <VirtualFileSnapshot>
                  <RelativePath>..\User\lvgl\src\font\lv_font_loader.c</RelativePath>
                </VirtualFileSnapshot>
                <VirtualFileSnapshot>
                  <RelativePath>..\User\lvgl\src\font\lv_font_montserrat_8.c</RelativePath>
                </VirtualFileSnapshot>
                <VirtualFileSnapshot>
                  <RelativePath>..\User\lvgl\src\font\lv_font_montserrat_10.c</RelativePath>
                </VirtualFileSnapshot>
                <VirtualFileSnapshot>
                  <RelativePath>..\User\lvgl\src\font\lv_font_montserrat_12.c</RelativePath>
                </VirtualFileSnapshot>
                <VirtualFileSnapshot>
                  <RelativePath>..\User\lvgl\src\font\lv_font_montserrat_12_subpx.c</RelativePath>
                </VirtualFileSnapshot>
                <VirtualFileSnapshot>
                  <RelativePath>..\User\lvgl\src\font\lv_font_montserrat_14.c</RelativePath>
                </VirtualFileSnapshot>
                <VirtualFileSnapshot>
                  <RelativePath>..\User\lvgl\src\font\lv_font_montserrat_16.c</RelativePath>
                </VirtualFileSnapshot>
                <VirtualFileSnapshot>
                  <RelativePath>..\User\lvgl\src\font\lv_font_montserrat_18.c</RelativePath>
                </VirtualFileSnapshot>
                <VirtualFileSnapshot>
                  <RelativePath>..\User\lvgl\src\font\lv_font_montserrat_20.c</RelativePath>
                </VirtualFileSnapshot>
                <VirtualFileSnapshot>
                  <RelativePath>..\User\lvgl\src\font\lv_font_montserrat_22.c</RelativePath>
                </VirtualFileSnapshot>
                <VirtualFileSnapshot>
                  <RelativePath>..\User\lvgl\src\font\lv_font_montserrat_24.c</RelativePath>
                </VirtualFileSnapshot>
                <VirtualFileSnapshot>
                  <RelativePath>..\User\lvgl\src\font\lv_font_montserrat_26.c</RelativePath>
                </VirtualFileSnapshot>
                <VirtualFileSnapshot>
                  <RelativePath>..\User\lvgl\src\font\lv_font_montserrat_28.c</RelativePath>
                </VirtualFileSnapshot>
                <VirtualFileSnapshot>
                  <RelativePath>..\User\lvgl\src\font\lv_font_montserrat_28_compressed.c</RelativePath>
                </VirtualFileSnapshot>
                <VirtualFileSnapshot>
                  <RelativePath>..\User\lvgl\src\font\lv_font_montserrat_30.c</RelativePath>
                </VirtualFileSnapshot>
                <VirtualFileSnapshot>
                  <RelativePath>..\User\lvgl\src\font\lv_font_montserrat_32.c</RelativePath>
                </VirtualFileSnapshot>
                <VirtualFileSnapshot>
                  <RelativePath>..\User\lvgl\src\font\lv_font_montserrat_34.c</RelativePath>
                </VirtualFileSnapshot>
                <VirtualFileSnapshot>
                  <RelativePath>..\User\lvgl\src\font\lv_font_montserrat_36.c</RelativePath>
                </VirtualFileSnapshot>
                <VirtualFileSnapshot>
                  <RelativePath>..\User\lvgl\src\font\lv_font_montserrat_38.c</RelativePath>
                </VirtualFileSnapshot>
                <VirtualFileSnapshot>
                  <RelativePath>..\User\lvgl\src\font\lv_font_montserrat_40.c</RelativePath>
                </VirtualFileSnapshot>
                <VirtualFileSnapshot>
                  <RelativePath>..\User\lvgl\src\font\lv_font_montserrat_42.c</RelativePath>
                </VirtualFileSnapshot>
                <VirtualFileSnapshot>
                  <RelativePath>..\User\lvgl\src\font\lv_font_montserrat_44.c</RelativePath>
                </VirtualFileSnapshot>
                <VirtualFileSnapshot>
                  <RelativePath>..\User\lvgl\src\font\lv_font_montserrat_46.c</RelativePath>
                </VirtualFileSnapshot>
                <VirtualFileSnapshot>
                  <RelativePath>..\User\lvgl\src\font\lv_font_montserrat_48.c</RelativePath>
                </VirtualFileSnapshot>
                <VirtualFileSnapshot>
                  <RelativePath>..\User\lvgl\src\font\lv_font_simsun_16_cjk.c</RelativePath>
                </VirtualFileSnapshot>
                <VirtualFileSnapshot>
                  <RelativePath>..\User\lvgl\src\font\lv_font_unscii_8.c</RelativePath>
                </VirtualFileSnapshot>
                <VirtualFileSnapshot>
                  <RelativePath>..\User\lvgl\src\font\lv_font_unscii_16.c</RelativePath>
                </VirtualFileSnapshot>
              </Files>
            </VirtualDirectorySnapshot>
            <VirtualDirectorySnapshot>
              <Name>GPU</Name>
              <Files />
            </VirtualDirectorySnapshot>
            <VirtualDirectorySnapshot>
              <Name>HAL</Name>
              <Files>
                <VirtualFileSnapshot>
                  <RelativePath>..\User\lvgl\src\hal\lv_hal_disp.c</RelativePath>
                </VirtualFileSnapshot>
                <VirtualFileSnapshot>
                  <RelativePath>..\User\lvgl\src\hal\lv_hal_indev.c</RelativePath>
                </VirtualFileSnapshot>
                <VirtualFileSnapshot>
                  <RelativePath>..\User\lvgl\src\hal\lv_hal_tick.c</RelativePath>
                </VirtualFileSnapshot>
              </Files>
            </VirtualDirectorySnapshot>
            <VirtualDirectorySnapshot>
              <Name>MISC</Name>
              <Files>
                <VirtualFileSnapshot>
                  <RelativePath>..\User\lvgl\src\misc\lv_anim.c</RelativePath>
                </VirtualFileSnapshot>
                <VirtualFileSnapshot>
                  <RelativePath>..\User\lvgl\src\misc\lv_anim_timeline.c</RelativePath>
                </VirtualFileSnapshot>
                <VirtualFileSnapshot>
                  <RelativePath>..\User\lvgl\src\misc\lv_area.c</RelativePath>
                </VirtualFileSnapshot>
                <VirtualFileSnapshot>
                  <RelativePath>..\User\lvgl\src\misc\lv_async.c</RelativePath>
                </VirtualFileSnapshot>
                <VirtualFileSnapshot>
                  <RelativePath>..\User\lvgl\src\misc\lv_bidi.c</RelativePath>
                </VirtualFileSnapshot>
                <VirtualFileSnapshot>
                  <RelativePath>..\User\lvgl\src\misc\lv_color.c</RelativePath>
                </VirtualFileSnapshot>
                <VirtualFileSnapshot>
                  <RelativePath>..\User\lvgl\src\misc\lv_fs.c</RelativePath>
                </VirtualFileSnapshot>
                <VirtualFileSnapshot>
                  <RelativePath>..\User\lvgl\src\misc\lv_gc.c</RelativePath>
                </VirtualFileSnapshot>
                <VirtualFileSnapshot>
                  <RelativePath>..\User\lvgl\src\misc\lv_ll.c</RelativePath>
                </VirtualFileSnapshot>
                <VirtualFileSnapshot>
                  <RelativePath>..\User\lvgl\src\misc\lv_log.c</RelativePath>
                </VirtualFileSnapshot>
                <VirtualFileSnapshot>
                  <RelativePath>..\User\lvgl\src\misc\lv_math.c</RelativePath>
                </VirtualFileSnapshot>
                <VirtualFileSnapshot>
                  <RelativePath>..\User\lvgl\src\misc\lv_mem.c</RelativePath>
                </VirtualFileSnapshot>
                <VirtualFileSnapshot>
                  <RelativePath>..\User\lvgl\src\misc\lv_printf.c</RelativePath>
                </VirtualFileSnapshot>
                <VirtualFileSnapshot>
                  <RelativePath>..\User\lvgl\src\misc\lv_style.c</RelativePath>
                </VirtualFileSnapshot>
                <VirtualFileSnapshot>
                  <RelativePath>..\User\lvgl\src\misc\lv_style_gen.c</RelativePath>
                </VirtualFileSnapshot>
                <VirtualFileSnapshot>
                  <RelativePath>..\User\lvgl\src\misc\lv_templ.c</RelativePath>
                </VirtualFileSnapshot>
                <VirtualFileSnapshot>
                  <RelativePath>..\User\lvgl\src\misc\lv_timer.c</RelativePath>
                </VirtualFileSnapshot>
                <VirtualFileSnapshot>
                  <RelativePath>..\User\lvgl\src\misc\lv_tlsf.c</RelativePath>
                </VirtualFileSnapshot>
                <VirtualFileSnapshot>
                  <RelativePath>..\User\lvgl\src\misc\lv_txt.c</RelativePath>
                </VirtualFileSnapshot>
                <VirtualFileSnapshot>
                  <RelativePath>..\User\lvgl\src\misc\lv_txt_ap.c</RelativePath>
                </VirtualFileSnapshot>
                <VirtualFileSnapshot>
                  <RelativePath>..\User\lvgl\src\misc\lv_utils.c</RelativePath>
                </VirtualFileSnapshot>
              </Files>
            </VirtualDirectorySnapshot>
            <VirtualDirectorySnapshot>
              <Name>WIDGETS</Name>
              <Files>
                <VirtualFileSnapshot>
                  <RelativePath>..\User\lvgl\src\widgets\lv_arc.c</RelativePath>
                </VirtualFileSnapshot>
                <VirtualFileSnapshot>
                  <RelativePath>..\User\lvgl\src\widgets\lv_bar.c</RelativePath>
                </VirtualFileSnapshot>
                <VirtualFileSnapshot>
                  <RelativePath>..\User\lvgl\src\widgets\lv_btn.c</RelativePath>
                </VirtualFileSnapshot>
                <VirtualFileSnapshot>
                  <RelativePath>..\User\lvgl\src\widgets\lv_btnmatrix.c</RelativePath>
                </VirtualFileSnapshot>
                <VirtualFileSnapshot>
                  <RelativePath>..\User\lvgl\src\widgets\lv_canvas.c</RelativePath>
                </VirtualFileSnapshot>
                <VirtualFileSnapshot>
                  <RelativePath>..\User\lvgl\src\widgets\lv_checkbox.c</RelativePath>
                </VirtualFileSnapshot>
                <VirtualFileSnapshot>
                  <RelativePath>..\User\lvgl\src\widgets\lv_dropdown.c</RelativePath>
                </VirtualFileSnapshot>
                <VirtualFileSnapshot>
                  <RelativePath>..\User\lvgl\src\widgets\lv_img.c</RelativePath>
                </VirtualFileSnapshot>
                <VirtualFileSnapshot>
                  <RelativePath>..\User\lvgl\src\widgets\lv_label.c</RelativePath>
                </VirtualFileSnapshot>
                <VirtualFileSnapshot>
                  <RelativePath>..\User\lvgl\src\widgets\lv_line.c</RelativePath>
                </VirtualFileSnapshot>
                <VirtualFileSnapshot>
                  <RelativePath>..\User\lvgl\src\widgets\lv_objx_templ.c</RelativePath>
                </VirtualFileSnapshot>
                <VirtualFileSnapshot>
                  <RelativePath>..\User\lvgl\src\widgets\lv_roller.c</RelativePath>
                </VirtualFileSnapshot>
                <VirtualFileSnapshot>
                  <RelativePath>..\User\lvgl\src\widgets\lv_slider.c</RelativePath>
                </VirtualFileSnapshot>
                <VirtualFileSnapshot>
                  <RelativePath>..\User\lvgl\src\widgets\lv_switch.c</RelativePath>
                </VirtualFileSnapshot>
                <VirtualFileSnapshot>
                  <RelativePath>..\User\lvgl\src\widgets\lv_table.c</RelativePath>
                </VirtualFileSnapshot>
                <VirtualFileSnapshot>
                  <RelativePath>..\User\lvgl\src\widgets\lv_textarea.c</RelativePath>
                </VirtualFileSnapshot>
              </Files>
            </VirtualDirectorySnapshot>
            <VirtualDirectorySnapshot>
              <Name>PORTING</Name>
              <Files>
                <VirtualFileSnapshot>
                  <RelativePath>..\User\lvgl\examples\porting\lv_port_disp.c</RelativePath>
                </VirtualFileSnapshot>
                <VirtualFileSnapshot>
                  <RelativePath>..\User\lvgl\examples\porting\lv_port_fs.c</RelativePath>
                </VirtualFileSnapshot>
                <VirtualFileSnapshot>
                  <RelativePath>..\User\lvgl\examples\porting\lv_port_indev.c</RelativePath>
                </VirtualFileSnapshot>
              </Files>
            </VirtualDirectorySnapshot>
            <VirtualDirectorySnapshot>
              <Name>THEMES</Name>
              <Files />
            </VirtualDirectorySnapshot>
            <VirtualDirectorySnapshot>
              <Name>DEMOS</Name>
              <Files>
                <VirtualFileSnapshot>
                  <RelativePath>..\User\lvgl\demos\widgets\lv_demo_widgets.c</RelativePath>
                </VirtualFileSnapshot>
                <VirtualFileSnapshot>
                  <RelativePath>..\User\lvgl\demos\widgets\assets\img_clothes.c</RelativePath>
                </VirtualFileSnapshot>
                <VirtualFileSnapshot>
                  <RelativePath>..\User\lvgl\demos\widgets\assets\img_demo_widgets_avatar.c</RelativePath>
                </VirtualFileSnapshot>
                <VirtualFileSnapshot>
                  <RelativePath>..\User\lvgl\demos\widgets\assets\img_lvgl_logo.c</RelativePath>
                </VirtualFileSnapshot>
              </Files>
            </VirtualDirectorySnapshot>
            <VirtualDirectorySnapshot>
              <Name>EXAM</Name>
              <Subdirectories>
                <VirtualDirectorySnapshot>
                  <Name>ASS</Name>
                  <Files>
                    <VirtualFileSnapshot>
                      <RelativePath>..\User\lvgl\examples\assets\animimg001.c</RelativePath>
                    </VirtualFileSnapshot>
                    <VirtualFileSnapshot>
                      <RelativePath>..\User\lvgl\examples\assets\animimg002.c</RelativePath>
                    </VirtualFileSnapshot>
                    <VirtualFileSnapshot>
                      <RelativePath>..\User\lvgl\examples\assets\animimg003.c</RelativePath>
                    </VirtualFileSnapshot>
                    <VirtualFileSnapshot>
                      <RelativePath>..\User\lvgl\examples\assets\img_caret_down.c</RelativePath>
                    </VirtualFileSnapshot>
                    <VirtualFileSnapshot>
                      <RelativePath>..\User\lvgl\examples\assets\img_cogwheel_alpha16.c</RelativePath>
                    </VirtualFileSnapshot>
                    <VirtualFileSnapshot>
                      <RelativePath>..\User\lvgl\examples\assets\img_cogwheel_argb.c</RelativePath>
                    </VirtualFileSnapshot>
                    <VirtualFileSnapshot>
                      <RelativePath>..\User\lvgl\examples\assets\img_cogwheel_chroma_keyed.c</RelativePath>
                    </VirtualFileSnapshot>
                    <VirtualFileSnapshot>
                      <RelativePath>..\User\lvgl\examples\assets\img_cogwheel_indexed16.c</RelativePath>
                    </VirtualFileSnapshot>
                    <VirtualFileSnapshot>
                      <RelativePath>..\User\lvgl\examples\assets\img_cogwheel_rgb.c</RelativePath>
                    </VirtualFileSnapshot>
                    <VirtualFileSnapshot>
                      <RelativePath>..\User\lvgl\examples\assets\img_hand.c</RelativePath>
                    </VirtualFileSnapshot>
                    <VirtualFileSnapshot>
                      <RelativePath>..\User\lvgl\examples\assets\img_skew_strip.c</RelativePath>
                    </VirtualFileSnapshot>
                    <VirtualFileSnapshot>
                      <RelativePath>..\User\lvgl\examples\assets\img_star.c</RelativePath>
                    </VirtualFileSnapshot>
                    <VirtualFileSnapshot>
                      <RelativePath>..\User\lvgl\examples\assets\imgbtn_left.c</RelativePath>
                    </VirtualFileSnapshot>
                    <VirtualFileSnapshot>
                      <RelativePath>..\User\lvgl\examples\assets\imgbtn_mid.c</RelativePath>
                    </VirtualFileSnapshot>
                    <VirtualFileSnapshot>
                      <RelativePath>..\User\lvgl\examples\assets\imgbtn_right.c</RelativePath>
                    </VirtualFileSnapshot>
                    <VirtualFileSnapshot>
                      <RelativePath>..\User\lvgl\examples\widgets\animimg\lv_example_animimg_1.c</RelativePath>
                    </VirtualFileSnapshot>
                  </Files>
                </VirtualDirectorySnapshot>
                <VirtualDirectorySnapshot>
                  <Name>EVE</Name>
                  <Files>
                    <VirtualFileSnapshot>
                      <RelativePath>..\User\lvgl\examples\event\lv_example_event_1.c</RelativePath>
                    </VirtualFileSnapshot>
                    <VirtualFileSnapshot>
                      <RelativePath>..\User\lvgl\examples\event\lv_example_event_2.c</RelativePath>
                    </VirtualFileSnapshot>
                    <VirtualFileSnapshot>
                      <RelativePath>..\User\lvgl\examples\event\lv_example_event_3.c</RelativePath>
                    </VirtualFileSnapshot>
                  </Files>
                </VirtualDirectorySnapshot>
                <VirtualDirectorySnapshot>
                  <Name>LAY</Name>
                  <Files>
                    <VirtualFileSnapshot>
                      <RelativePath>..\User\lvgl\examples\layouts\flex\lv_example_flex_1.c</RelativePath>
                    </VirtualFileSnapshot>
                    <VirtualFileSnapshot>
                      <RelativePath>..\User\lvgl\examples\layouts\flex\lv_example_flex_2.c</RelativePath>
                    </VirtualFileSnapshot>
                    <VirtualFileSnapshot>
                      <RelativePath>..\User\lvgl\examples\layouts\flex\lv_example_flex_3.c</RelativePath>
                    </VirtualFileSnapshot>
                    <VirtualFileSnapshot>
                      <RelativePath>..\User\lvgl\examples\layouts\flex\lv_example_flex_4.c</RelativePath>
                    </VirtualFileSnapshot>
                    <VirtualFileSnapshot>
                      <RelativePath>..\User\lvgl\examples\layouts\flex\lv_example_flex_5.c</RelativePath>
                    </VirtualFileSnapshot>
                    <VirtualFileSnapshot>
                      <RelativePath>..\User\lvgl\examples\layouts\flex\lv_example_flex_6.c</RelativePath>
                    </VirtualFileSnapshot>
                  </Files>
                </VirtualDirectorySnapshot>
              </Subdirectories>
              <Files>
                <VirtualFileSnapshot>
                  <RelativePath>..\User\lvgl\examples\anim\lv_example_anim_1.c</RelativePath>
                </VirtualFileSnapshot>
                <VirtualFileSnapshot>
                  <RelativePath>..\User\lvgl\examples\anim\lv_example_anim_2.c</RelativePath>
                </VirtualFileSnapshot>
                <VirtualFileSnapshot>
                  <RelativePath>..\User\lvgl\examples\anim\lv_example_anim_3.c</RelativePath>
                </VirtualFileSnapshot>
                <VirtualFileSnapshot>
                  <RelativePath>..\User\lvgl\examples\anim\lv_example_anim_timeline_1.c</RelativePath>
                </VirtualFileSnapshot>
              </Files>
            </VirtualDirectorySnapshot>
            <VirtualDirectorySnapshot>
              <Name>EX</Name>
              <Subdirectories>
                <VirtualDirectorySnapshot>
                  <Name>WIN</Name>
                  <Files>
                    <VirtualFileSnapshot>
                      <RelativePath>..\User\lvgl\examples\widgets\win\lv_example_win_1.c</RelativePath>
                    </VirtualFileSnapshot>
                  </Files>
                </VirtualDirectorySnapshot>
                <VirtualDirectorySnapshot>
                  <Name>LA</Name>
                  <Files>
                    <VirtualFileSnapshot>
                      <RelativePath>..\User\lvgl\examples\widgets\label\lv_example_label_1.c</RelativePath>
                    </VirtualFileSnapshot>
                    <VirtualFileSnapshot>
                      <RelativePath>..\User\lvgl\examples\widgets\label\lv_example_label_2.c</RelativePath>
                    </VirtualFileSnapshot>
                    <VirtualFileSnapshot>
                      <RelativePath>..\User\lvgl\examples\widgets\label\lv_example_label_3.c</RelativePath>
                    </VirtualFileSnapshot>
                    <VirtualFileSnapshot>
                      <RelativePath>..\User\lvgl\examples\widgets\label\lv_example_label_4.c</RelativePath>
                    </VirtualFileSnapshot>
                  </Files>
                </VirtualDirectorySnapshot>
                <VirtualDirectorySnapshot>
                  <Name>ME</Name>
                  <Files>
                    <VirtualFileSnapshot>
                      <RelativePath>..\User\lvgl\examples\widgets\meter\lv_example_meter_1.c</RelativePath>
                    </VirtualFileSnapshot>
                    <VirtualFileSnapshot>
                      <RelativePath>..\User\lvgl\examples\widgets\meter\lv_example_meter_2.c</RelativePath>
                    </VirtualFileSnapshot>
                    <VirtualFileSnapshot>
                      <RelativePath>..\User\lvgl\examples\widgets\meter\lv_example_meter_3.c</RelativePath>
                    </VirtualFileSnapshot>
                    <VirtualFileSnapshot>
                      <RelativePath>..\User\lvgl\examples\widgets\meter\lv_example_meter_4.c</RelativePath>
                    </VirtualFileSnapshot>
                  </Files>
                </VirtualDirectorySnapshot>
                <VirtualDirectorySnapshot>
                  <Name>BA</Name>
                  <Files>
                    <VirtualFileSnapshot>
                      <RelativePath>..\User\lvgl\examples\widgets\bar\lv_example_bar_1.c</RelativePath>
                    </VirtualFileSnapshot>
                    <VirtualFileSnapshot>
                      <RelativePath>..\User\lvgl\examples\widgets\bar\lv_example_bar_2.c</RelativePath>
                    </VirtualFileSnapshot>
                    <VirtualFileSnapshot>
                      <RelativePath>..\User\lvgl\examples\widgets\bar\lv_example_bar_3.c</RelativePath>
                    </VirtualFileSnapshot>
                    <VirtualFileSnapshot>
                      <RelativePath>..\User\lvgl\examples\widgets\bar\lv_example_bar_4.c</RelativePath>
                    </VirtualFileSnapshot>
                    <VirtualFileSnapshot>
                      <RelativePath>..\User\lvgl\examples\widgets\bar\lv_example_bar_5.c</RelativePath>
                    </VirtualFileSnapshot>
                    <VirtualFileSnapshot>
                      <RelativePath>..\User\lvgl\examples\widgets\bar\lv_example_bar_6.c</RelativePath>
                    </VirtualFileSnapshot>
                  </Files>
                </VirtualDirectorySnapshot>
                <VirtualDirectorySnapshot>
                  <Name>BT</Name>
                  <Files>
                    <VirtualFileSnapshot>
                      <RelativePath>..\User\lvgl\examples\widgets\btn\lv_example_btn_1.c</RelativePath>
                    </VirtualFileSnapshot>
                    <VirtualFileSnapshot>
                      <RelativePath>..\User\lvgl\examples\widgets\btn\lv_example_btn_2.c</RelativePath>
                    </VirtualFileSnapshot>
                    <VirtualFileSnapshot>
                      <RelativePath>..\User\lvgl\examples\widgets\btn\lv_example_btn_3.c</RelativePath>
                    </VirtualFileSnapshot>
                    <VirtualFileSnapshot>
                      <RelativePath>..\User\lvgl\examples\widgets\btnmatrix\lv_example_btnmatrix_1.c</RelativePath>
                    </VirtualFileSnapshot>
                    <VirtualFileSnapshot>
                      <RelativePath>..\User\lvgl\examples\widgets\btnmatrix\lv_example_btnmatrix_2.c</RelativePath>
                    </VirtualFileSnapshot>
                    <VirtualFileSnapshot>
                      <RelativePath>..\User\lvgl\examples\widgets\btnmatrix\lv_example_btnmatrix_3.c</RelativePath>
                    </VirtualFileSnapshot>
                  </Files>
                </VirtualDirectorySnapshot>
              </Subdirectories>
              <Files />
            </VirtualDirectorySnapshot>
            <VirtualDirectorySnapshot>
              <Name>USER</Name>
              <Files>
                <VirtualFileSnapshot>
                  <RelativePath>..\User\lvgl\user\test1.c</RelativePath>
                </VirtualFileSnapshot>
              </Files>
            </VirtualDirectorySnapshot>
          </Subdirectories>
          <Files>
            <VirtualFileSnapshot>
              <RelativePath>..\User\lvgl\timer.c</RelativePath>
            </VirtualFileSnapshot>
            <VirtualFileSnapshot>
              <RelativePath>..\User\lv_conf.h</RelativePath>
            </VirtualFileSnapshot>
          </Files>
        </VirtualDirectorySnapshot>
      </Subdirectories>
      <Files />
    </RootDirectory>
    <Configurations>
      <ImportedConfiguration>
        <IsStaticLibrary>false</IsStaticLibrary>
        <Settings>
          <IncludeDirectories>
            <string>..\Libraries\CMSIS</string>
            <string>..\User</string>
            <string>..\Libraries\FWlib\inc</string>
            <string>..\User\lvgl</string>
            <string>..\User\lvgl\examples\porting</string>
            <string>..\User\lvgl\demos\widgets</string>
            <string>..\User\lvgl\examples\anim</string>
            <string>..\User\lvgl\examples\widgets</string>
            <string>..\User\lvgl\src\extra\widgets\animimg</string>
            <string>..\User\lvgl\examples\event</string>
            <string>..\User\lvgl\user</string>
            <string>..\User\lvgl\examples\layouts\flex</string>
          </IncludeDirectories>
          <PreprocessorMacros>
            <string>$$com.sysprogs.bspoptions.primary_memory$$_layout</string>
            <string>STM32F10X_HD</string>
            <string>USE_STDPERIPH_DRIVER</string>
          </PreprocessorMacros>
          <GeneratePreprocessorOutput>false</GeneratePreprocessorOutput>
          <IsDebugConfiguration>false</IsDebugConfiguration>
        </Settings>
      </ImportedConfiguration>
    </Configurations>
  </ImportedProject>
</EmbeddedProfile>